quillmark_mcp/__init__.py
quillmark_mcp/__main__.py
quillmark_mcp/models.py
quillmark_mcp/quill_loader.py
quillmark_mcp/server.py
quillmark_mcp/tools/__init__.py
tonguetoquill-collection/.gitignore
tonguetoquill-collection/LICENSE
tonguetoquill-collection/quills/taro/Quill.toml
tonguetoquill-collection/quills/taro/glue.typ
tonguetoquill-collection/quills/taro/taro.md
tonguetoquill-collection/quills/taro/assets/Figtree-Bold.ttf
tonguetoquill-collection/quills/taro/assets/Figtree-Italic.ttf
tonguetoquill-collection/quills/taro/assets/Figtree-Regular.ttf
tonguetoquill-collection/quills/usaf_memo/.quillignore
tonguetoquill-collection/quills/usaf_memo/Quill.toml
tonguetoquill-collection/quills/usaf_memo/glue.typ
tonguetoquill-collection/quills/usaf_memo/usaf_memo.md
tonguetoquill-collection/quills/usaf_memo/assets/CopperplateCC-Heavy.otf
tonguetoquill-collection/quills/usaf_memo/assets/DejaVuSansMono-Bold.ttf
tonguetoquill-collection/quills/usaf_memo/assets/DejaVuSansMono-BoldOblique.ttf
tonguetoquill-collection/quills/usaf_memo/assets/DejaVuSansMono-Oblique.ttf
tonguetoquill-collection/quills/usaf_memo/assets/DejaVuSansMono.ttf
tonguetoquill-collection/quills/usaf_memo/assets/NimbusRomNo9L-Med.otf
tonguetoquill-collection/quills/usaf_memo/assets/NimbusRomNo9L-MedIta.otf
tonguetoquill-collection/quills/usaf_memo/assets/NimbusRomNo9L-Reg.otf
tonguetoquill-collection/quills/usaf_memo/assets/NimbusRomNo9L-RegIta.otf
tonguetoquill-collection/quills/usaf_memo/assets/dod_seal.gif
tonguetoquill-collection/quills/usaf_memo/assets/dow_seal.png
tonguetoquill-collection/quills/usaf_memo/packages/tonguetoquill-usaf-memo/.gitignore
tonguetoquill-collection/quills/usaf_memo/packages/tonguetoquill-usaf-memo/LICENSE
tonguetoquill-collection/quills/usaf_memo/packages/tonguetoquill-usaf-memo/typst.toml
tonguetoquill-collection/quills/usaf_memo/packages/tonguetoquill-usaf-memo/src/lib.typ
tonguetoquill-collection/quills/usaf_memo/packages/tonguetoquill-usaf-memo/src/utils.typ
quillmark_mcp-0.0.10.dist-info/METADATA
quillmark_mcp-0.0.10.dist-info/WHEEL
quillmark_mcp-0.0.10.dist-info/entry_points.txt
quillmark_mcp-0.0.10.dist-info/licenses/LICENSE
quillmark_mcp-0.0.10.dist-info/RECORD
