Metadata-Version: 2.4
Name: quillmark-mcp
Version: 0.0.10
Summary: MCP server for Quillmark document rendering. Run with `quillmark-mcp@0.0.8` (recommended).
Project-URL: Homepage, https://github.com/yourusername/quillmark-mcp
Project-URL: Repository, https://github.com/yourusername/quillmark-mcp
Project-URL: Issues, https://github.com/yourusername/quillmark-mcp/issues
Author-email: Your Name <your.email@example.com>
License: MIT
License-File: LICENSE
Keywords: document-rendering,markdown,mcp,model-context-protocol,quillmark,typst
Classifier: Development Status :: 3 - Alpha
Classifier: Intended Audience :: Developers
Classifier: License :: OSI Approved :: MIT License
Classifier: Programming Language :: Python :: 3.10
Classifier: Programming Language :: Python :: 3.11
Classifier: Programming Language :: Python :: 3.12
Requires-Python: >=3.10
Requires-Dist: mcp>=0.1.0
Requires-Dist: pydantic>=2.0
Requires-Dist: quillmark>=0.1.17
Requires-Dist: tomli>=2.0.0; python_version < '3.11'
Provides-Extra: dev
Requires-Dist: pytest-asyncio>=0.23; extra == 'dev'
Requires-Dist: pytest>=8.0; extra == 'dev'
Requires-Dist: tbump; extra == 'dev'
